{
  "parent": "minecraft:recipes/root",
  "criteria": {
    "has_the_recipe": {
      "conditions": {
        "recipe": "tgears:crafting/part/whisk"
      },
      "trigger": "minecraft:recipe_unlocked"
    },
    "has_whisk_cast": {
      "conditions": {
        "items": [
          {
            "items": [
              "tgears:whisk_cast"
            ]
          }
        ]
      },
      "trigger": "minecraft:inventory_changed"
    }
  },
  "requirements": [
    [
      "has_whisk_cast",
      "has_the_recipe"
    ]
  ],
  "rewards": {
    "recipes": [
      "tgears:crafting/part/whisk"
    ]
  },
  "sends_telemetry_event": false
}